[
  {
    "slug": "search-console-pages-rapport-ny",
    "title": "Ny Search Console-rapport: 'Pages' giver nye indsigter",
    "excerpt": "Google Search Console introducerer en ny rapport, der giver dybere indsigt i sideperformance og indeksstatus.",
    "date": "2025-08-25",
    "tags": ["search console","pages","indeks"]
  },
  {
    "slug": "ai-overview-aendringer-eu-2025",
    "title": "Google tester ændringer i AI Overviews i EU",
    "excerpt": "AI Overviews justeres i EU med nye krav til transparens og kildeangivelser.",
    "date": "2025-08-24",
    "tags": ["ai overviews","google","eu"]
  },
  {
    "slug": "discover-kvalitetssignaler-opdateres",
    "title": "Discover: Kvalitetssignaler opdateres for friskt indhold",
    "excerpt": "Google Discover prioriterer nu opdaterede artikler og friskt indhold endnu højere.",
    "date": "2025-08-23",
    "tags": ["discover","indhold","kvalitet"]
  },
  {
    "slug": "core-web-vitals-inp-vejledning",
    "title": "Ny INP-vejledning: interaktivitet og lange tasks",
    "excerpt": "Google udsender en officiel vejledning til hvordan du forbedrer INP som en del af Core Web Vitals.",
    "date": "2025-08-22",
    "tags": ["core web vitals","inp","google"]
  },
  {
    "slug": "gsc-api-udvider-dimensioner",
    "title": "GSC API udvider dimensioner: device + country i samme forespørgsel",
    "excerpt": "Ny funktion i Google Search Console API gør det muligt at kombinere dimensioner i rapporter.",
    "date": "2025-08-21",
    "tags": ["gsc api","device","country"]
  },
  {
    "slug": "schema-faq-policy-opdatering",
    "title": "Schema FAQ: Politikker opdateret for bedre relevans",
    "excerpt": "Google strammer kravene til FAQ markup for at sikre mere relevant brug.",
    "date": "2025-08-20",
    "tags": ["schema","faq","structured data"]
  },
  {
    "slug": "local-pack-foto-krav",
    "title": "Local Pack: Nye anbefalinger til billeder i profiler",
    "excerpt": "Google anbefaler højere billedkvalitet og specifikke størrelser i lokale profiler.",
    "date": "2025-08-19",
    "tags": ["local pack","billeder","lokal seo"]
  },
  {
    "slug": "shopping-structured-data-varer",
    "title": "Shopping-resultater: Structured data for varianter præciseres",
    "excerpt": "Google tydeliggør hvordan du markerer produktvarianter i structured data.",
    "date": "2025-08-18",
    "tags": ["shopping","structured data","produkter"]
  },
  {
    "slug": "ranking-signaler-myte-aflivning",
    "title": "Google afliver endnu en myte om ‘hemmelige rankingsignaler’",
    "excerpt": "I en Q&A understreger Googles team at der ikke findes skjulte signaler udenfor dokumentation.",
    "date": "2025-08-17",
    "tags": ["ranking","google","myter"]
  },
  {
    "slug": "bing-indexnow-udvidelser",
    "title": "IndexNow: Flere CMS-plugins opdateres til hurtigere ping",
    "excerpt": "Flere store CMS’er udvider deres integrationer med IndexNow-protokollen.",
    "date": "2025-08-16",
    "tags": ["bing","indexnow","cms"]
  }
]
